alexcalculator/__init__.py
alexcalculator/alexcalculator.py
alexcalculator-0.0.2.dist-info/LICENSE
alexcalculator-0.0.2.dist-info/METADATA
alexcalculator-0.0.2.dist-info/WHEEL
alexcalculator-0.0.2.dist-info/top_level.txt
alexcalculator-0.0.2.dist-info/RECORD
