Metadata-Version: 2.1
Name: alexcalculator
Version: 0.0.2
Summary: This is very basic calculator
Home-page: UNKNOWN
Author: Alex Gomes
Author-email: alexandergoomezzz@gmail.com
License: UNKNOWN
Platform: UNKNOWN
License-File: LICENSE
